{"moduleName":null,"summaries":[{"symbol":{"__symbol":0,"members":[]},"metadata":{"__symbol":1,"members":[]}},{"symbol":{"__symbol":2,"members":[]},"metadata":{"__symbol":3,"members":[]}},{"symbol":{"__symbol":4,"members":[]},"metadata":{"__symbol":5,"members":[]}},{"symbol":{"__symbol":6,"members":[]},"metadata":{"__symbol":7,"members":[]}},{"symbol":{"__symbol":8,"members":[]},"metadata":{"__symbol":9,"members":[]}},{"symbol":{"__symbol":10,"members":[]},"metadata":{"__symbol":11,"members":[]}},{"symbol":{"__symbol":12,"members":[]},"metadata":{"__symbol":13,"members":[]}},{"symbol":{"__symbol":14,"members":[]},"metadata":{"__symbol":15,"members":[]}},{"symbol":{"__symbol":16,"members":[]},"metadata":{"__symbol":17,"members":[]}},{"symbol":{"__symbol":18,"members":[]},"metadata":{"__symbol":19,"members":[]}}],"symbols":[{"__symbol":0,"name":"AnimationsService","filePath":"./ngx-nowbrains-animations"},{"__symbol":1,"name":"AnimationsService","filePath":"./public-api"},{"__symbol":2,"name":"FadeInOut","filePath":"./ngx-nowbrains-animations"},{"__symbol":3,"name":"FadeInOut","filePath":"./public-api"},{"__symbol":4,"name":"FadeSlideInOut","filePath":"./ngx-nowbrains-animations"},{"__symbol":5,"name":"FadeSlideInOut","filePath":"./public-api"},{"__symbol":6,"name":"FadeSlideInOutKonversoOpacityOut","filePath":"./ngx-nowbrains-animations"},{"__symbol":7,"name":"FadeSlideInOutKonversoOpacityOut","filePath":"./public-api"},{"__symbol":8,"name":"FadeSlideInOutKonversoTranslateOut","filePath":"./ngx-nowbrains-animations"},{"__symbol":9,"name":"FadeSlideInOutKonversoTranslateOut","filePath":"./public-api"},{"__symbol":10,"name":"FadeSlideInOutCasesFeedHome","filePath":"./ngx-nowbrains-animations"},{"__symbol":11,"name":"FadeSlideInOutCasesFeedHome","filePath":"./public-api"},{"__symbol":12,"name":"FadeSlideInOutStagger","filePath":"./ngx-nowbrains-animations"},{"__symbol":13,"name":"FadeSlideInOutStagger","filePath":"./public-api"},{"__symbol":14,"name":"SlideRightAndLeft","filePath":"./ngx-nowbrains-animations"},{"__symbol":15,"name":"SlideRightAndLeft","filePath":"./public-api"},{"__symbol":16,"name":"slideInOut","filePath":"./ngx-nowbrains-animations"},{"__symbol":17,"name":"slideInOut","filePath":"./public-api"},{"__symbol":18,"name":"FlipX","filePath":"./ngx-nowbrains-animations"},{"__symbol":19,"name":"FlipX","filePath":"./public-api"}]}